MANIFEST.in
README.md
setup.py
custom_auth/__init__.py
custom_auth/admin.py
custom_auth/auth.py
custom_auth/forms.py
custom_auth/models.py
custom_auth/tests.py
custom_auth/urls.py
custom_auth/views.py
custom_auth/migrations/0001_initial.py
custom_auth/migrations/0001_initial.pyc
custom_auth/migrations/__init__.py
custom_auth/migrations/__init__.pyc
custom_auth/templates/custom_auth/activate.html
custom_auth/templates/custom_auth/login.html
custom_auth/templates/custom_auth/logout.html
custom_auth/templates/custom_auth/manage.html
custom_auth/templates/custom_auth/profile.html
custom_auth/templates/custom_auth/register.html
custom_auth/templates/custom_auth/registration_successful.html
django_custom_auth.egg-info/PKG-INFO
django_custom_auth.egg-info/SOURCES.txt
django_custom_auth.egg-info/dependency_links.txt
django_custom_auth.egg-info/top_level.txt