Metadata-Version: 1.1
Name: django-custom-auth
Version: 0.1.2
Summary: A simple Django app that replaces the default authentication
Home-page: https://github.com/endthestart/django-custom-auth
Author: Michael Anderson
Author-email: contact@andermic.com
License: BSD License
Platform: UNKNOWN
Classifier: Environment :: Web Environment
Classifier: Framework :: Django
Classifier: Intended Audience :: Developers
Classifier: License :: OSI Approved :: BSD License
Classifier: Operating System :: OS Independent
Classifier: Programming Language :: Python
Classifier: Programming Language :: Python :: 2.6
Classifier: Programming Language :: Python :: 2.7
Classifier: Topic :: Internet :: WWW/HTTP
Classifier: Topic :: Internet :: WWW/HTTP :: Dynamic Content
